stm32pio/cli/__init__.py
stm32pio/cli/__main__.py
stm32pio/cli/app.py
stm32pio/core/__init__.py
stm32pio/core/clean.py
stm32pio/core/config.py
stm32pio/core/cubemx.py
stm32pio/core/log.py
stm32pio/core/pio.py
stm32pio/core/project.py
stm32pio/core/settings.py
stm32pio/core/state.py
stm32pio/core/util.py
stm32pio/core/validate.py
stm32pio/core/version.py
stm32pio/gui/__init__.py
stm32pio/gui/__main__.py
stm32pio/gui/app.py
stm32pio/gui/list.py
stm32pio/gui/log.py
stm32pio/gui/project.py
stm32pio/gui/settings.py
stm32pio/gui/util.py
stm32pio/gui/icons/add.svg
stm32pio/gui/icons/drop-here.svg
stm32pio/gui/icons/edit.svg
stm32pio/gui/icons/icon.svg
stm32pio/gui/icons/remove.svg
stm32pio/gui/icons/trash-bin.svg
stm32pio/gui/qml/AboutDialog.qml
stm32pio/gui/qml/ActionButton.qml
stm32pio/gui/qml/App.qml
stm32pio/gui/qml/DropHereToAdd.qml
stm32pio/gui/qml/InitScreen.qml
stm32pio/gui/qml/LogArea.qml
stm32pio/gui/qml/ProjectActionsModel.qml
stm32pio/gui/qml/ProjectsListFooter.qml
stm32pio/gui/qml/ProjectsListItem.qml
stm32pio/gui/qml/SettingsDialog.qml
stm32pio-2.1.2.dist-info/LICENSE
stm32pio-2.1.2.dist-info/METADATA
stm32pio-2.1.2.dist-info/WHEEL
stm32pio-2.1.2.dist-info/entry_points.txt
stm32pio-2.1.2.dist-info/top_level.txt
stm32pio-2.1.2.dist-info/RECORD
