Metadata-Version: 2.1
Name: stm32pio
Version: 2.1.2
Summary: Small cross-platform Python app that can create and update PlatformIO projects from STM32CubeMX .ioc files. It uses STM32CubeMX to generate a HAL-framework-based code and alongside creates PlatformIO project with compatible parameters to stick them both together. Both CLI and GUI editions are available
Home-page: https://github.com/ussserrr/stm32pio
Author: ussserrr
Author-email: andrei4.2008@gmail.com
License: MIT License
Keywords: platformio,stm32cubemx,stm32,cubemx
Platform: UNKNOWN
Classifier: Programming Language :: Python :: 3 :: Only
Classifier: License :: OSI Approved :: MIT License
Classifier: Development Status :: 5 - Production/Stable
Classifier: Operating System :: MacOS :: MacOS X
Classifier: Operating System :: Microsoft :: Windows
Classifier: Operating System :: Unix
Classifier: Environment :: Console
Classifier: Environment :: MacOS X
Classifier: Environment :: Win32 (MS Windows)
Classifier: Environment :: X11 Applications :: Qt
Classifier: Natural Language :: English
Classifier: Topic :: Software Development :: Embedded Systems
Requires-Python: >=3.6
Provides-Extra: GUI
License-File: LICENSE
